slides_cli/__init__.py
slides_cli/build.py
slides_cli/export.py
slides_cli/inflate.py
slides_cli/init.py
slides_cli/main.py
slides_cli/new.py
slides_cli/preview.py
slides_cli/tutorial.py
slides_cli/update.py
slides_cli/utils.py
slides_cli/view.py
slides_cli/tutorials/0.basic.md
slides_cli/tutorials/1.reveal.theme.md
slides_cli/tutorials/2.reveal.template.md
slides_cli/tutorials/__init__.py
slipy/__init__.py
slipy/build.py
slipy/export.py
slipy/inflate.py
slipy/new.py
slipy/preview.py
slipy/update.py
slipy/version.py
slipy/view.py
slipy/beamer/__init__.py
slipy/reveal/__init__.py
slipy/reveal/assets.py
slipy/reveal/get.py
slipy/reveal/reload.py
slipy/reveal/view.py
slipy/reveal/httpwatcher/build/httpwatcher.bundle.js
slipy/utils/__init__.py
slipy/utils/archive.py
slipy/utils/clipng.py
slipy/utils/log.py
slipy_assets/__init__.py
slipy_assets/presentation.toml
slipy_assets/beamer/__init__.py
slipy_assets/reveal/__init__.py
slipy_assets/reveal/reveal.toml
slipy_assets/reveal/templates/README.md
slipy_assets/reveal/templates/md_split/README.md
slipy_assets/reveal/templates/md_split/build.py
slipy_assets/reveal/templates/md_split/options.toml
slipy_assets/reveal/templates/md_split/template.html
slipy_assets/reveal/templates/md_split/examples/0.html
slipy_assets/reveal/templates/md_split/examples/1.md
slipy_assets/reveal/templates/md_split/examples/2.md
slipy_assets/reveal/templates/md_split/examples/3.md
slipy_assets/reveal/templates/md_split/examples/foot.html
slipy_assets/reveal/templates/md_split/examples/head.html
slipy_assets/reveal/templates/md_split/examples/assets/cover.png
slipy_assets/reveal/templates/md_split/examples/assets/favicon.png
slipy_assets/reveal/templates/split/README.md
slipy_assets/reveal/templates/split/build.py
slipy_assets/reveal/templates/split/options.toml
slipy_assets/reveal/templates/split/template.html
slipy_assets/reveal/templates/split/examples/0.html
slipy_assets/reveal/templates/split/examples/1.html
slipy-0.3.1.dist-info/METADATA
slipy-0.3.1.dist-info/WHEEL
slipy-0.3.1.dist-info/entry_points.txt
slipy-0.3.1.dist-info/top_level.txt
slipy-0.3.1.dist-info/RECORD
