Metadata-Version: 2.1
Name: slipy
Version: 0.3.1
Summary: slides utility
Home-page: https://github.com/AleCandido/slipy
Author: A.Candido
Author-email: candido.ale@gmail.com
License: UNKNOWN
Platform: UNKNOWN
Classifier: Programming Language :: Python
Classifier: Programming Language :: Python :: 3
Requires-Python: >=3.7
Requires-Dist: toml
Requires-Dist: jinja2
Requires-Dist: python-frontmatter
Requires-Dist: pygit2
Requires-Dist: requests
Requires-Dist: websockets
Requires-Dist: watchdog
Requires-Dist: rich
Provides-Extra: utils
Requires-Dist: pyperclip ; extra == 'utils'
Requires-Dist: Pillow ; extra == 'utils'
